skywatchpy/KEYS.py
skywatchpy/__init__.py
skywatchpy/countries.py
skywatchpy/test.py
skywatchpy/weather.py
skywatchpy-0.1.1.dist-info/LICENSE
skywatchpy-0.1.1.dist-info/METADATA
skywatchpy-0.1.1.dist-info/WHEEL
skywatchpy-0.1.1.dist-info/top_level.txt
skywatchpy-0.1.1.dist-info/RECORD
