Metadata-Version: 2.1
Name: skywatchpy
Version: 0.1.1
Summary: UNKNOWN
Home-page: https://github.com/Abduraxmonnn/SkyWatchPy.git
Author: Abdurakhmon Asatullayev
Author-email: abduraxmonasatullayev35@gmail.com
License: MIT
Platform: UNKNOWN
License-File: LICENSE
Requires-Dist: requests
Requires-Dist: python-dotenv
